[
  {
    "type": "MultipleChoiceQuestion",
    "label": "My views and concerns were listened to",
    "note": null,
    "required": false,
    "variable": "$views_listened",
    "enableIf": null,
    "customValidations": [],
    "options": ["Always", "Mostly", "Sometimes", "Rarely", "Never", "Didn’t apply"],
    "minimumResponses": 0,
    "maximumResponses": 1,
    "valueMode": "index"
  },
  {
    "type": "MultipleChoiceQuestion",
    "label": "My individual needs were met",
    "note": null,
    "required": false,
    "variable": "$needs_met",
    "enableIf": null,
    "customValidations": [],
    "options": ["Always", "Mostly", "Sometimes", "Rarely", "Never"],
    "minimumResponses": 0,
    "maximumResponses": 1,
    "valueMode": "index"
  },
  {
    "type": "MultipleChoiceQuestion",
    "label": "When a need could not be met, staff explained why",
    "note": null,
    "required": false,
    "variable": "$needs_explained",
    "enableIf": "$needs_met && $needs_met[0] >= 2",
    "customValidations": [],
    "options": ["Always", "Mostly", "Sometimes", "Rarely", "Never"],
    "minimumResponses": 0,
    "maximumResponses": 1,
    "valueMode": "index"
  },
  {
    "type": "MultipleChoiceQuestion",
    "label": "I felt cared for",
    "note": null,
    "required": false,
    "variable": "$felt_cared",
    "enableIf": null,
    "customValidations": [],
    "options": ["Always", "Mostly", "Sometimes", "Rarely", "Never"],
    "minimumResponses": 0,
    "maximumResponses": 1,
    "valueMode": "index"
  },
  {
    "type": "MultipleChoiceQuestion",
    "label": "I was involved as much as I wanted in making decisions about my treatment and care",
    "note": null,
    "required": false,
    "variable": "$involved",
    "enableIf": null,
    "customValidations": [],
    "options": ["Always", "Mostly", "Sometimes", "Rarely", "Never"],
    "minimumResponses": 0,
    "maximumResponses": 1,
    "valueMode": "index"
  },
  {
    "type": "MultipleChoiceQuestion",
    "label": "I was kept informed as much as I wanted about my treatment and care",
    "note": null,
    "required": false,
    "variable": "$informed",
    "enableIf": null,
    "customValidations": [],
    "options": ["Always", "Mostly", "Sometimes", "Rarely", "Never"],
    "minimumResponses": 0,
    "maximumResponses": 1,
    "valueMode": "index"
  },
  {
    "type": "MultipleChoiceQuestion",
    "label": "As far as I could tell, the staff involved in my care communicated with each other about my treatment",
    "note": null,
    "required": false,
    "variable": "$team_communicated",
    "enableIf": null,
    "customValidations": [],
    "options": ["Always", "Mostly", "Sometimes", "Rarely", "Never", "Didn’t apply"],
    "minimumResponses": 0,
    "maximumResponses": 1,
    "valueMode": "index"
  },
  {
    "type": "MultipleChoiceQuestion",
    "label": "I received pain relief that met my needs",
    "note": null,
    "required": false,
    "variable": "$pain_relief",
    "enableIf": null,
    "customValidations": [],
    "options": ["Always", "Mostly", "Sometimes", "Rarely", "Never", "Didn’t apply"],
    "minimumResponses": 0,
    "maximumResponses": 1,
    "valueMode": "index"
  },
  {
    "type": "MultipleChoiceQuestion",
    "label": "When I was in the hospital, I felt confident in the safety of my treatment and care",
    "note": null,
    "required": false,
    "variable": "$confident_safety",
    "enableIf": null,
    "customValidations": [],
    "options": ["Always", "Mostly", "Sometimes", "Rarely", "Never"],
    "minimumResponses": 0,
    "maximumResponses": 1,
    "valueMode": "index"
  },
  {
    "type": "MultipleChoiceQuestion",
    "label": "I experienced unexpected harm or distress as a result of my treatment or care",
    "note": null,
    "required": false,
    "variable": "$harm_distress",
    "enableIf": null,
    "customValidations": [],
    "options": ["Yes, physical harm", "Yes, emotional distress", "Yes, both", "No"],
    "minimumResponses": 0,
    "maximumResponses": 1,
    "valueMode": "index"
  },
  {
    "type": "MultipleChoiceQuestion",
    "label": "My harm or distress was discussed with me by staff",
    "note": null,
    "required": false,
    "variable": "$harm_discussed",
    "enableIf": "$harm_distress && $harm_distress[0] !== 3",
    "customValidations": [],
    "options": ["Yes", "No", "Not sure", "Didn’t want to discuss it"],
    "minimumResponses": 0,
    "maximumResponses": 1,
    "valueMode": "index"
  },
  {
    "type": "MultipleChoiceQuestion",
    "label": "Overall, the quality of the treatment and care I received was:",
    "note": null,
    "required": false,
    "variable": "$overall_quality",
    "enableIf": null,
    "customValidations": [],
    "options": ["Very good", "Good", "Average", "Poor", "Very poor"],
    "minimumResponses": 0,
    "maximumResponses": 1,
    "valueMode": "index"
  }
]
